ncm_clp_dl/__init__.py
ncm_clp_dl/__main__.py
ncm_clp_dl-0.0.5.dist-info/LICENSE
ncm_clp_dl-0.0.5.dist-info/METADATA
ncm_clp_dl-0.0.5.dist-info/WHEEL
ncm_clp_dl-0.0.5.dist-info/entry_points.txt
ncm_clp_dl-0.0.5.dist-info/top_level.txt
ncm_clp_dl-0.0.5.dist-info/RECORD
